odoo10_addon_pos_quick_logout-10.0.1.0.1-py3.8-nspkg.pth
odoo/addons/pos_quick_logout/README.rst
odoo/addons/pos_quick_logout/__init__.py
odoo/addons/pos_quick_logout/__manifest__.py
odoo/addons/pos_quick_logout/i18n/ca.po
odoo/addons/pos_quick_logout/i18n/es.po
odoo/addons/pos_quick_logout/i18n/fr.po
odoo/addons/pos_quick_logout/i18n/hr_HR.po
odoo/addons/pos_quick_logout/i18n/it.po
odoo/addons/pos_quick_logout/i18n/nl_NL.po
odoo/addons/pos_quick_logout/i18n/pos_quick_logout.pot
odoo/addons/pos_quick_logout/models/__init__.py
odoo/addons/pos_quick_logout/models/pos_config.py
odoo/addons/pos_quick_logout/static/description/cashier_user_different.png
odoo/addons/pos_quick_logout/static/description/cashier_user_identical.png
odoo/addons/pos_quick_logout/static/description/icon.png
odoo/addons/pos_quick_logout/static/src/css/pos_quick_logout.css
odoo/addons/pos_quick_logout/static/src/js/pos_quick_logout.js
odoo/addons/pos_quick_logout/static/src/xml/pos_quick_logout.xml
odoo/addons/pos_quick_logout/static/src/xml/templates.xml
odoo/addons/pos_quick_logout/views/pos_config_view.xml
odoo10_addon_pos_quick_logout-10.0.1.0.1.dist-info/METADATA
odoo10_addon_pos_quick_logout-10.0.1.0.1.dist-info/WHEEL
odoo10_addon_pos_quick_logout-10.0.1.0.1.dist-info/namespace_packages.txt
odoo10_addon_pos_quick_logout-10.0.1.0.1.dist-info/top_level.txt
odoo10_addon_pos_quick_logout-10.0.1.0.1.dist-info/RECORD
